smqpp/__init__.py
smqpp/version.py
smqpp-0.1.5.dist-info/licenses/LICENSE
smqpp-0.1.5.dist-info/METADATA
smqpp-0.1.5.dist-info/WHEEL
smqpp-0.1.5.dist-info/top_level.txt
smqpp-0.1.5.dist-info/RECORD
