Metadata-Version: 2.4
Name: smqpp
Version: 0.1.5
Summary: Smartseq2 preprocessing toolkit
Home-page: https://github.com/SharonWang/smqpp
Author: Xiaonan Wang
Author-email: xw251@cam.ac.uk
License: MIT
License-File: LICENSE
Requires-Dist: numpy
Requires-Dist: matplotlib
Requires-Dist: pandas
Requires-Dist: anndata
Requires-Dist: scipy
Requires-Dist: statsmodels
Requires-Dist: patsy
Requires-Dist: umap
Dynamic: author
Dynamic: author-email
Dynamic: home-page
Dynamic: license
Dynamic: license-file
Dynamic: requires-dist
Dynamic: summary
